object_case_switcher/TransformStructure.py
object_case_switcher/__init__.py
object_case_switcher/transformFunctions.py
object_case_switcher/transformPropModule.py
object_case_switcher/utils.py
object_case_switcher-0.0.33.dist-info/LICENSE
object_case_switcher-0.0.33.dist-info/METADATA
object_case_switcher-0.0.33.dist-info/WHEEL
object_case_switcher-0.0.33.dist-info/top_level.txt
object_case_switcher-0.0.33.dist-info/RECORD
