Metadata-Version: 2.1
Name: object-case-switcher
Version: 0.0.33
Summary: The easiest way to switch case of prop in return of your functions
Home-page: https://github.com/Alex-Andr-19/case_switcher
Author: Aleksandrychev Andrey
Author-email: aleks-andr-19@yandex.ru
License: MIT License
Project-URL: GitHub, https://github.com/Alex-Andr-19/case_switcher
Keywords: case,switcher,python,snake,camel,switch
Platform: UNKNOWN
Classifier: Programming Language :: Python :: 3
Classifier: License :: OSI Approved :: MIT License
Classifier: Operating System :: OS Independent
Requires-Python: >=3.6
License-File: LICENSE
